{
    "Title": "\nAfter class\n",
    "Designer": "Wang Weibao (王維宝)Wang Xuetao (王雪涛)",
    "Date": "1974",
    "Publisher": "Rongbaozhai (荣宝斋)",
    "Size": "38x53 cm.",
    "Call nr.": "BG D25/7",
    "Collection": "Landsberger collection",
    "Notes": "",
    "Theme": "Table tennis",
    "Tags": [
        "China",
        "poster",
        "Chinese",
        "propaganda",
        "table tennis",
        "ping pong",
        "child",
        "blossom",
        "sports",
        "ethnic minorities",
        "1974",
        "乒乓球"
    ]
}