{
    "Title": "\nAmerican Relief Agency - Report on American relief work. 1\n",
    "Designer": "Designer unknown (佚名)",
    "Date": "1948",
    "Publisher": "United States Information Service",
    "Size": "35.5x25.5 cm.",
    "Call nr.": "BG D25/55",
    "Collection": "Landsberger collection",
    "Notes": "As part of the US$275 million agreement that was signed on 3 July 1948, the US provided 197,707 ton of grain and foodstuffs, part of which is being unloaded here.Nr. 1 of the poster set on the Economic Aid Agreement between the United States of America and the Republic of China (3 July 1948).",
    "Theme": "American Economic Aid (1948)",
    "Tags": [
        "China",
        "poster",
        "Chinese",
        "propaganda",
        "1948",
        "ship",
        "food",
        "truck",
        "harbor",
        "photograph",
        "dock",
        "Republic of China",
        "relief"
    ]
}