{
    "Title": "\nProtect yourself, keep SARS away\n",
    "Designer": "Huang Yijiu (黄一九)Mei Zhihao (梅志浩)",
    "Date": "2003",
    "Publisher": "Hunan kexue jishu chubanshe (湖南科学技术出版社)",
    "Size": "42.5x57.5 cm.",
    "Call nr.": "BG D25/49",
    "Collection": "Landsberger collection",
    "Notes": "",
    "Theme": "SARS and avian flu",
    "Tags": [
        "China",
        "poster",
        "Chinese",
        "propaganda",
        "SARS",
        "disease",
        "2003",
        "非典",
        "photograph"
    ]
}