{
    "Title": "\nWe have the right to vote and to be elected\n",
    "Designer": "Yang Xianrang (杨先让)",
    "Date": "1953, July",
    "Publisher": "Renmin meishu chubanshe (人民美术出版社), Beijing",
    "Size": "77x53.5 cm.",
    "Call nr.": "BG E12/370",
    "Collection": "IISH collection",
    "Notes": "Elections for the first peasants' and workers' councils.",
    "Theme": "Elections for Workers' and Peasants' Councils (1950-1955)",
    "Tags": [
        "China",
        "poster",
        "Chinese",
        "propaganda",
        "1953",
        "elections",
        "voting",
        "woman",
        "countryside",
        "voting rights",
        "councils",
        "ballot"
    ]
}