{
    "Title": "\nChairman Mao leads us to implement a real democratic election system\n",
    "Designer": "Designer unknown (佚名)",
    "Date": "ca. 1954",
    "Publisher": "",
    "Size": "77.5x53.5 cm.",
    "Call nr.": "BG E12/597",
    "Collection": "IISH collection",
    "Notes": "Mao casting his vote in Beijing, 8 December 1953, in the elections for the People's Congress.",
    "Theme": "Elections for Workers' and Peasants' Councils (1950-1955)",
    "Tags": [
        "China",
        "poster",
        "Chinese",
        "propaganda",
        "1954",
        "elections",
        "ballot box",
        "National People's Congress",
        "全国人民代表大会",
        "毛泽东",
        "photograph",
        "Mao",
        "Mao Zedong",
        "voting"
    ]
}