{
    "Title": "\nOde to Socialism -- Only socialism can save China, only socialism can develop China\n",
    "Designer": "Central Academy of Industrial Art and Design (中央工艺美术学院)",
    "Date": "1989, December",
    "Publisher": "Renmin jiaoyu chubanshe (人民教育出版社)",
    "Size": "77x53 cm.",
    "Call nr.": "BG E13/460",
    "Collection": "Landsberger collection",
    "Notes": "During the student demonstrations on Tiananmen square in Beijing in 1989, a white statue of the 'Goddess of Democracy' was erected. After the crushing of the demonstrations the authorities put this statue in its place.",
    "Theme": "People's Movement 1989Political Reform",
    "Tags": [
        "China",
        "poster",
        "北京",
        "statue",
        "propaganda",
        "Chinese",
        "1989",
        "Beijing",
        "photograph",
        "sculpture",
        "worker",
        "soldier",
        "peasant",
        "rifle",
        "puddling rod",
        "grain",
        "intellectual",
        "national flag",
        "sun",
        "socialism"
    ]
}