{
    "Title": "\nA grand occasion during National Day in the Capital\n",
    "Designer": "Zhang Yuqing (章育青)",
    "Date": "1986, June",
    "Publisher": "Shanghai renmin meishu chubanshe (上海人民美术出版社)",
    "Size": "53x77 cm.",
    "Call nr.": "BG E13/223",
    "Collection": "Landsberger collection",
    "Notes": "",
    "Theme": "1 October, National Day of the People's Republic of China",
    "Tags": [
        "China",
        "poster",
        "Chinese",
        "propaganda",
        "1986",
        "parade",
        "rocket",
        "balloon",
        "北京",
        "1 October Parade",
        "天安门",
        "Beijing",
        "Tian'anmen",
        "streamer",
        "pennant",
        "ICBM",
        "People's Liberation Army",
        "Jiefangjun",
        "jet fighter",
        "banner",
        "Mao portrait",
        "soldier",
        "National Day",
        "国庆节",
        "missile",
        "解放军",
        "39.903333, 116.391667"
    ]
}