{
    "Title": "\nBuild up a good physique, steel the will, to contribute strength to the realization of the Four Modernizations\n",
    "Designer": "Liang Zhaotang (梁照堂)Li Xingtao (李醒滔)",
    "Date": "1979, July",
    "Publisher": "Renmin tiyu chubanshe (人民美术出版社)",
    "Size": "105x77 cm.",
    "Call nr.": "BG E13/371",
    "Collection": "Landsberger collection",
    "Notes": "",
    "Theme": "Sports",
    "Tags": [
        "China",
        "poster",
        "swimming",
        "swimsuit",
        "woman",
        "propaganda",
        "Chinese",
        "1979",
        "bridge",
        "river",
        "Four Modernizations",
        "四化"
    ]
}