{
    "Title": "\nThe Yan'an Spirit is passed on from generation to generation\n",
    "Designer": "Zuo Jianhua (左建华)",
    "Date": "1974, April",
    "Publisher": "Tianjin renmin meishu chubanshe (天津人民美术出版社)",
    "Size": "54x78 cm.",
    "Call nr.": "BG E13/810",
    "Collection": "Landsberger collection",
    "Notes": "",
    "Theme": "Yan'an",
    "Tags": [
        "China",
        "poster",
        "Chinese",
        "propaganda",
        "1974",
        "Yan'an",
        "延安",
        "cave dwelling",
        "lattice",
        "Mao portrait",
        "child",
        "Pioneers",
        "Eating Bitterness",
        "teacher",
        "peasant",
        "straw hat",
        "satchel",
        "red flag",
        "desk",
        "36.598578, 109.487171"
    ]
}