{
    "Title": "\nI'm a little artist\n",
    "Designer": "Liu Bingli (刘秉礼)",
    "Date": "1985, July",
    "Publisher": "Guangzhou branch Kexue puji chubanshe (科学普及出版社广州分社)",
    "Size": "77x53 cm.",
    "Call nr.": "BG E13/239",
    "Collection": "Landsberger collection",
    "Notes": "",
    "Theme": "Visualizing the FutureSocialist Spiritual Civilization (1980-2000)Song & Dance",
    "Tags": [
        "China",
        "poster",
        "Chinese",
        "propaganda",
        "1985",
        "boy",
        "cap",
        "guitar",
        "girl",
        "dancer",
        "dancing",
        "balloon"
    ]
}