{
    "Title": "\nLei Feng and the red scarves\n",
    "Designer": "Xu Fugen (徐福根)",
    "Date": "1982, May",
    "Publisher": "Renmin meishu chubanshe (人民美术出版社)",
    "Size": "77x53 cm.",
    "Call nr.": "BG E13/15",
    "Collection": "Landsberger collection",
    "Notes": "",
    "Theme": "Lei FengModels and MartyrsSocialist Spiritual Civilization (1980-2000)",
    "Tags": [
        "China",
        "poster",
        "Chinese",
        "propaganda",
        "1982",
        "Lei Feng",
        "雷锋",
        "child",
        "flowers",
        "scarf",
        "pencil",
        "book"
    ]
}