{
    "Title": "\nFamous people, famous words -- Hua Luogeng\n",
    "Designer": "Yan Jie (燕杰)Kang Zhuang (康庄)",
    "Date": "1996, March",
    "Publisher": "Neimenggu daxue chubanshe (内蒙古大学出版社)",
    "Size": "108x35.5 cm.",
    "Call nr.": "BG E13/519",
    "Collection": "Landsberger collection",
    "Notes": "Hua Luogeng (华罗庚) or Hua Loo-Keng (1910-1985) was a mathematician and politician famous for his important contributions to number theory and for his role as the leader of mathematics research and education in China.\"Famous people, famous words\" is an educational series from 1996, presenting a number of famous persons, both Chinese and foreign, and their famous utterances. This quote from Hua Luogeng reads: \"Genius lies in accumulation, cleverness lies in hard work\" (天才在于积累，聪明在于勤奋).",
    "Theme": "Socialist Spiritual Civilization (1980-2000)Visualizing the Future",
    "Tags": [
        "China",
        "poster",
        "Chinese",
        "propaganda",
        "1996",
        "Hua Luogeng",
        "华罗庚",
        "quotation"
    ]
}