{
    "Title": "\nFour seasons sports activities (summer)\n",
    "Designer": "Zhu Youru (朱友儒)Bai Xueshi (白雪石)",
    "Date": "1958, October",
    "Publisher": "Renmin tiyu chubanshe (人民美术出版社), Beijing",
    "Size": "77x36 cm.",
    "Call nr.": "BG E14/994",
    "Collection": "IISH collection",
    "Notes": "This poster belongs to a series of four, each one depicting a season. We only have this one.",
    "Theme": "",
    "Tags": [
        "China",
        "poster",
        "Chinese",
        "propaganda",
        "1958",
        "landscape",
        "countryside",
        "swimming",
        "paddy",
        "summer",
        "river",
        "Four Seasons"
    ]
}