{
    "Title": "\nIncrease culture, to create a modernized, regular army for national defense!\n",
    "Designer": "Lu Delin (卢德麟)",
    "Date": "1952, August",
    "Publisher": "Jiefangjun huabaoshe (解放军画报社)",
    "Size": "78x54 cm.",
    "Call nr.": "BG E15/942",
    "Collection": "Landsberger collection",
    "Notes": "",
    "Theme": "People's Liberation ArmyForeign Friends: North Korea",
    "Tags": [
        "China",
        "poster",
        "Chinese",
        "propaganda",
        "1952",
        "People's Liberation Army",
        "Selected Works of Mao Zedong",
        "Mao Zedong xuanji",
        "毛泽东选集",
        "book",
        "tank",
        "red flag",
        "jet fighter",
        "warship",
        "soldier",
        "machine gun",
        "medal",
        "解放军"
    ]
}