{
    "Title": "\nOrganize the people's militia on a big scale in the movements to study Dazhai and Daqing -- Third of four propaganda posters commemorating the 20th anniversary of Chairman Mao's instruction to \"organize contingents of the people's militia on a big scale\"\n",
    "Designer": "Propaganda Department of the Shanxi Provincial Communist Party Committee (中共山西省委宣传部)Political Department of the Shanxi Provincial Military Region (山西省军区政治部)",
    "Date": "1978, September",
    "Publisher": "Publisher unknown",
    "Size": "53.5x76.5 cm.",
    "Call nr.": "BG E15/457",
    "Collection": "Landsberger collection",
    "Notes": "The banner in the right hand corner reads (partially) \"Shock troop\" (突击队).",
    "Theme": "People's MilitiaDazhaiDaqingWorking Women",
    "Tags": [
        "China",
        "poster",
        "Chinese",
        "propaganda",
        "1978",
        "people's militia",
        "民兵",
        "red flag",
        "bugle",
        "miner",
        "woman",
        "tractor",
        "terrace",
        "transmission tower",
        "derrick",
        "shoulder protector",
        "护肩",
        "Dazhai",
        "Daqing",
        "大寨",
        "大庆",
        "rifle"
    ]
}