{
    "Title": "\nSavagely attack to hurt the rightists elements, to protect the results of socialism!\n",
    "Designer": "Wuhan Branch of Chinese Artist Association (中国美术家协会武汉分会)",
    "Date": "1957, October",
    "Publisher": "Changjiang wenyi chubanshe (长江文艺出版社)",
    "Size": "53x77 cm.",
    "Call nr.": "BG E15/669",
    "Collection": "Landsberger collection",
    "Notes": "",
    "Theme": "Double-Hundred Policy (1956-1957)",
    "Tags": [
        "China",
        "poster",
        "Chinese",
        "propaganda",
        "1957",
        "Anti-Rightist Struggle",
        "cartoon",
        "反右运动"
    ]
}