{
    "Title": "\nXiang Xiuli\n",
    "Designer": "Zhang Yuejian (张岳健)",
    "Date": "1961, June",
    "Publisher": "Shanghai jiaoyu chubanshe (上海教育出版社)",
    "Size": "53x77 cm.",
    "Call nr.": "BG E15/775",
    "Collection": "Landsberger collection",
    "Notes": "This is a print from the second edition (July 1961).",
    "Theme": "Xiang Xiuli",
    "Tags": [
        "China",
        "poster",
        "Chinese",
        "propaganda",
        "Xiang Xiuli",
        "向秀丽",
        "martyr",
        "fire",
        "1961",
        "chemicals",
        "flames"
    ]
}