{
    "Title": "\nPresenting red flowers to the hero(es), millions of 'Iron Men' surge like a tide\n",
    "Designer": "Jin Jifa (金纪发)",
    "Date": "1977, March",
    "Publisher": "Shanghai renmin chubanshe (上海人民出版社)",
    "Size": "77x106 cm.",
    "Call nr.": "BG E15/540",
    "Collection": "Landsberger collection",
    "Notes": "",
    "Theme": "Models and MartyrsWang JinxiVisualizing the Future",
    "Tags": [
        "China",
        "poster",
        "Chinese",
        "propaganda",
        "1977",
        "Wang Jinxi",
        "miner",
        "steel worker",
        "flowers",
        "award",
        "model worker",
        "fur hat",
        "王进喜"
    ]
}