{
    "Title": "\nDevelop industry, take steel as the key link\n",
    "Designer": "Feng Jianqin (冯建亲)Chen Dexi (陈德曦)",
    "Date": "1976, January",
    "Publisher": "Jiangsu renmin chubanshe (江苏人民出版社)",
    "Size": "53x77 cm.",
    "Call nr.": "BG E15/378",
    "Collection": "Landsberger collection",
    "Notes": "",
    "Theme": "",
    "Tags": [
        "China",
        "poster",
        "Chinese",
        "propaganda",
        "1976",
        "steel worker",
        "blast furnace",
        "banner",
        "slogan",
        "steel",
        "steel mill",
        "puddling rod",
        "钢钎"
    ]
}