{
    "Title": "\nThe prospects for agriculture are infinitely good, the laboring young people are infinitely happy\n",
    "Designer": "Ren Xing (任兴)",
    "Date": "1964, April",
    "Publisher": "Tianjin meishu chubanshe (天津美术出版社)",
    "Size": "54x77 cm.",
    "Call nr.": "BG E15/338",
    "Collection": "Landsberger collection",
    "Notes": "",
    "Theme": "",
    "Tags": [
        "China",
        "poster",
        "Chinese",
        "propaganda",
        "1964",
        "sent-down youth",
        "tractor",
        "flute",
        "transmission tower",
        "straw hat",
        "swallow",
        "grain",
        "agriculture"
    ]
}