{
    "Title": "\nChairman Mao's former residence Shaoshan\n",
    "Designer": "Designer unknown (佚名)",
    "Date": "1971, January",
    "Publisher": "Tianjin renmin meishu chubanshe (天津人民美术出版社)",
    "Size": "53x77 cm.",
    "Call nr.": "BG E15/251",
    "Collection": "Landsberger collection",
    "Notes": "",
    "Theme": "Shaoshan",
    "Tags": [
        "China",
        "poster",
        "Chinese",
        "propaganda",
        "1971",
        "Shaoshan",
        "韶山",
        "farm",
        "photograph",
        "farmhouse",
        "red flag",
        "danwei tourism",
        "27.884, 112.532"
    ]
}