{
    "Title": "\nLei Feng -- educational posters of heroic persons\n",
    "Designer": "Qin Dahu (秦大虎)Jin Qingjin (靳庆金)",
    "Date": "1992, May",
    "Publisher": "Shanghai jiaoyu chubanshe (上海教育出版社)",
    "Size": "78x53 cm.",
    "Call nr.": "BG E15/409",
    "Collection": "Landsberger collection",
    "Notes": "",
    "Theme": "Lei FengModels and MartyrsSocialist Spiritual Civilization (1980-2000)",
    "Tags": [
        "China",
        "poster",
        "Chinese",
        "propaganda",
        "1992",
        "Lei Feng",
        "truck",
        "washing",
        "medal",
        "model",
        "雷锋",
        "Jiefang",
        "解放"
    ]
}