{
    "Title": "\nCheer for overfulfilling the quota of 10.700.000 tons of steel\n",
    "Designer": "Lu Xingchen (陆星辰)Shen Lin (沈霖)",
    "Date": "1958, December",
    "Publisher": "Shanghai renmin meishu chubanshe  (上海人民美术出版社)",
    "Size": "78x54 cm.",
    "Call nr.": "BG E16/270",
    "Collection": "IISH collection",
    "Notes": "",
    "Theme": "Great Leap Forward (1958-1961)",
    "Tags": [
        "China",
        "poster",
        "Chinese",
        "propaganda",
        "1958",
        "steel",
        "fireworks",
        "searchlight",
        "industrial plant",
        "blast furnace",
        "photomontage",
        "Great Leap Forward",
        "大跃进",
        "night"
    ]
}