{
    "Title": "\nGo to the countryside, go to the border areas, go to the places where the motherland needs you the most\n",
    "Designer": "Designer unknown (佚名)",
    "Date": "1970, February",
    "Publisher": "Shanghaishi gemingzu (上海市革命组)",
    "Size": "77x53 cm.",
    "Call nr.": "BG E16/331",
    "Collection": "IISH collection",
    "Notes": "The train has departed from Shanghai (上海).The text in the image reads:It is absolutely necessary for the educated youth to go to the countryside to receive re-education from the Poor and Lower-Middle peasants (知识青年到农村去，接受贫下中农的再教育，很有必要)The slogan on the train reads:Always learn from comrade Jin Xunhua (向金训华同志学习)",
    "Theme": "Up to the mountains, down to the villages (1968)",
    "Tags": [
        "China",
        "poster",
        "train",
        "propaganda",
        "Chinese",
        "毛主席语录",
        "1970",
        "Mao badge",
        "Mao button",
        "xiafang qingnian",
        "下放青年",
        "zhiqing",
        "知青",
        "Quotations from Chairman Mao",
        "Mao Zhuxi Yulu",
        "rusticated youth",
        "Little Red Book",
        "sent-down youth",
        "Jin Xunhua"
    ]
}