{
    "Title": "\nCertainly put the establishment of new rural villages in the hands of this generation of ours\n",
    "Designer": "Sha Gengsi (沙更思)",
    "Date": "1961, March",
    "Publisher": "Renmin meishu chubanshe (人民美术出版社)",
    "Size": "54x78 cm.",
    "Call nr.": "BG E18/32",
    "Collection": "Landsberger collection",
    "Notes": "One of the early sent-down youth, blowing in his fist to warm his hand.The text on the flag is the same as the title of the poster.",
    "Theme": "Great Leap Forward (1958-1961)",
    "Tags": [
        "China",
        "poster",
        "Chinese",
        "propaganda",
        "1961",
        "countryside",
        "sent-down youth",
        "fur hat",
        "tractor",
        "sun",
        "hoe",
        "wasteland reclamation",
        "Great Leap Forward",
        "大跃进"
    ]
}