{
    "Title": "\nEarthquake destruction and the reduction of disaster popularization charts\n",
    "Designer": "National Seismological Administration (国家地震局)",
    "Date": "1992, April",
    "Publisher": "Dizhen chubanshe (地震出版社)",
    "Size": "53x38 cm.",
    "Call nr.": "BG E37/927",
    "Collection": "Landsberger collection",
    "Notes": "\"Earthquake destruction and the reduction of disaster popularization charts\" (地震灾害与减灾科普挂图) is a 12-poster series published in 1992 by the National Seismological Administration.Entitled \"When disaster strikes one side, support comes from all sides\" (一方有灾 八方支援), the poster shows relief goods being flown in by helicopter, and other examples of solidarity.",
    "Theme": "Earthquakes",
    "Tags": [
        "China",
        "poster",
        "Chinese",
        "propaganda",
        "1992",
        "earthquake",
        "disaster relief",
        "helicopter",
        "box",
        "pledge",
        "handshake"
    ]
}