{
    "Title": "\nWe will certainly storm the fortress of science\n",
    "Designer": "You Longgu (游龙姑)",
    "Date": "1955, July",
    "Publisher": "Shanghai renmin meishu chubanshe (上海人民美术出版社)",
    "Size": "52x77 cm.",
    "Call nr.": "BG E37/844",
    "Collection": "Landsberger collection",
    "Notes": "This is a print from the second impression (February 1957).",
    "Theme": "",
    "Tags": [
        "China",
        "poster",
        "Chinese",
        "propaganda",
        "1955",
        "student",
        "cadre",
        "laboratory",
        "test tube",
        "chart",
        "fountain pen"
    ]
}