{
    "Title": "\nWorkers and peasants unite to make everything like spring\n",
    "Designer": "Huang Miaofa (黄妙发)",
    "Date": "1962, October",
    "Publisher": "Shanghai renmin meishu chubanshe (上海人民美术出版社)",
    "Size": "53x68 cm.",
    "Call nr.": "BG E37/914",
    "Collection": "Landsberger collection",
    "Notes": "This poster is from the 6th edition, July 1964, with a total print run of 832,000 copies.",
    "Theme": "Door Gods (门神)",
    "Tags": [
        "China",
        "poster",
        "Chinese",
        "propaganda",
        "1962",
        "miner",
        "steel worker",
        "peasant",
        "drill",
        "coal",
        "grain",
        "rails",
        "cotton",
        "door gods",
        "menshen",
        "门神",
        "puddling rod",
        "钢钎"
    ]
}