{
    "Title": "\nLong live the dictatorship of the proletariat\n",
    "Designer": "Zhejiang gong nong bing huabaoshe (浙江工农兵画报社)",
    "Date": "1971, March",
    "Publisher": "Zhejiang renmin chubanshe (浙江人民出版社)",
    "Size": "77x106 cm.",
    "Call nr.": "BG E39/606",
    "Collection": "IISH collection",
    "Notes": "",
    "Theme": "Karl MarxShanghai People's Commune (1967)",
    "Tags": [
        "China",
        "poster",
        "Chinese",
        "propaganda",
        "1971",
        "flag",
        "cannon",
        "rifle",
        "Paris",
        "马克思",
        "Vendôme Column",
        "barricade",
        "Paris Commune",
        "Commune de Paris",
        "Karl Marx"
    ]
}