{
    "Title": "\nChairman Mao is the reddest, reddest red sun in the hearts of all the people of the world\n",
    "Designer": "Revolutionary Committee of Guangzhou Academy of Fine Arts (广州美术学院革命委員)",
    "Date": "1969, February",
    "Publisher": "Guangdong Provincial Publication and Distribution Station for the Collected Works of Chairman Mao (毛主席著作广东省出版发行站)",
    "Size": "32x54 cm.",
    "Call nr.": "PC-1969-s-002",
    "Collection": "Private collection",
    "Notes": "",
    "Theme": "Foreign FriendsThe Mao Cult",
    "Tags": [
        "China",
        "poster",
        "Chinese",
        "propaganda",
        "1969",
        "毛泽东",
        "毛主席语录",
        "lantern",
        "handshake",
        "Mao Zhuxi Yulu",
        "Quotations from Chairman Mao",
        "Mao Zedong",
        "Little Red Book",
        "Africans",
        "Arabs",
        "Albanians",
        "Latin American",
        "Korean"
    ]
}