{
    "Title": "\nThe spirit of Lei Feng has developed greatly, selling junk to the state is done with great force\n",
    "Designer": "Designer unknown (佚名)",
    "Date": "Early 1970s",
    "Publisher": "Hebei sheng Shijiazhuang diqu tuchan gongsi (河北省石家庄地区土产公司), Shijiazhuang",
    "Size": "26x77 cm.",
    "Call nr.": "PC-197a-006",
    "Collection": "Private collection",
    "Notes": "Collecting assorted junk, including bottles, is made part of the Lei Feng spirit of devotion and contribution to the state. Poster published by the Hebei Province Shijiazhuang area local products company.Part of a series of four.",
    "Theme": "Recycling",
    "Tags": [
        "China",
        "poster",
        "Chinese",
        "propaganda",
        "child",
        "basket",
        "recycling",
        "waste",
        "oil drum",
        "Pioneers"
    ]
}