{
    "Title": "\nGreat tank battle\n",
    "Designer": "Designer unknown (佚名)",
    "Date": "ca. 1938",
    "Publisher": "Lushan huapian gongsi (廬山畫片公司), Shanghai ",
    "Size": "53x79 cm.",
    "Call nr.": "PC-193b-005",
    "Collection": "Private collection",
    "Notes": "",
    "Theme": "The Second Sino-Japanese War (1937-1945)",
    "Tags": [
        "China",
        "poster",
        "Chinese",
        "propaganda",
        "1938",
        "airplane",
        "tank",
        "War of Resistance Against Japan",
        "Second Sino-Japanese War",
        "抗日战争",
        "coast",
        "artillery",
        "Republic of China"
    ]
}