{
    "Title": "\nThe Chairman leads the building of the new China\n",
    "Designer": "Yang Junsheng (杨俊生)",
    "Date": "1950",
    "Publisher": "Huamei huapianshe (华美画片社) Shanghai",
    "Size": "78.5x54.5 cm.",
    "Call nr.": "PC-1950-002",
    "Collection": "Private collection",
    "Notes": "Mao Zedong and Zhu De on horseback, as if still on a military campaign. In the background industrial installations and power masts are being built.",
    "Theme": "Early Industrialization (1950-1955)",
    "Tags": [
        "China",
        "poster",
        "horse",
        "industry",
        "毛泽东",
        "propaganda",
        "Chinese",
        "transmission tower",
        "electricity pylon",
        "1950",
        "construction",
        "朱德",
        "Zhu De",
        "Mao Zedong",
        "early industrialization"
    ]
}