{
    "Title": "\nThe mountains and the open country are green, fruit trees are plentiful, the people's lives are boundlessly happy\n",
    "Designer": "Ye Ming (叶明)",
    "Date": "1959, August",
    "Publisher": "Tianjin shaonian ertong meishu chubanshe (天津少年儿童美术出版社)",
    "Size": "76.5x53 cm.",
    "Call nr.": "PC-1959-017",
    "Collection": "Private collection",
    "Notes": "",
    "Theme": "National Minorities",
    "Tags": [
        "China",
        "poster",
        "Chinese",
        "propaganda",
        "1959",
        "grapes",
        "harvest",
        "Uyghur",
        "ethnic minorities",
        "braid"
    ]
}