{
    "Title": "\nEmbroidering Moscow\n",
    "Designer": "Fei Xinwo (费新我)",
    "Date": "1959, March",
    "Publisher": "Tianjin meishu chubanshe (天津美术出版社)",
    "Size": "53.5x38 cm.",
    "Call nr.": "PC-1959-s-001",
    "Collection": "Private collection",
    "Notes": "A group of women preparing to make a large embroidery of the Moscow Kremlin. The woman on the ladder chair studies the picture from which the line drawing on the canvas has been made, while other women are sorting out colored threads.",
    "Theme": "Foreign Friends: Soviet Union",
    "Tags": [
        "China",
        "poster",
        "Chinese",
        "propaganda",
        "1959",
        "Moscow",
        "Kremlin",
        "Spasskaya Tower",
        "embroidery",
        "woman"
    ]
}