{
    "post_author": "Propagandopolis",
    "upload_date": "June 22, 2023",
    "region": "North America, United States",
    "tags": [
        "1940",
        " New Deal",
        " Pin",
        " USA"
    ],
    "title": "Sure! I’m for the New Deal – I.M.A. SIMP (American pin, 1940)",
    "Text": " Sure! I’m for the New Deal – I.M.A. SIMP.",
    "Year": " 1940.",
    "Publisher": " Republican Wendell Willkie’s presidential campaign.",
    "Artist": " NA.",
    "Additional Information": " Pin attacking President Roosevelt and the New Deal. Issued as part of Republican Wendell Willkie’s presidential campaign, the pin shows the grinning character of ‘Ima Simp’ (meaning ‘simpleton’), implying that supporters of Roosevelt and the New Deal are somewhat dim."
}