{
    "post_author": "Propagandopolis",
    "upload_date": "July 3, 2023",
    "region": "Europe, Soviet Union",
    "tags": [
        "1972",
        " Azerbaijan",
        " Fighting Pencil",
        " Joseph Efimovsky",
        " USSR"
    ],
    "title": "Stars of Azerbaijan (Soviet poster, ca. 1972)",
    "Text": " Stars of Azerbaijan. Respect and fame through labour earned, / By fisherman, oil worker, gardner or shepherd. / With confidence, side by side with friends / An equal among equals strides our Azerbaijan!",
    "Year": " ca. 1972.",
    "Publisher": " Fighting Pencil.",
    "Artist": " Joseph Efimovsky.",
    "Additional Information": " Shows Azerbaijani workers walking along a boardwalk wearing their Hero of Socialist Labour medals."
}