{
    "Creator": "United States Food Administration. Food Committee State Council of Defense. Federal Food Administrator for Washington.",
    "Date (Original)": "1916~",
    "Description": "52 x 70 cm. Color. Poster aimed at encouraging the use of potatoes over wheat-based products by listing the potato&#x27;s attributes.",
    "Digitization": "Original items were scanned as 600 dpi tiffs on a Zeutschel OS 14000 A0-LS scanner. They were converted to jpegs (sized at 3000 pixels on the long dimension) using Adobe Photoshop CS2 they and subsequently uploaded into CONTENTdm.",
    "Identifier": "sc005f11-047",
    "Language": "English",
    "Publisher": "United States Food Administration. Food Committee State Council of Defense. Federal Food Administrator for Washington.",
    "Rights": "http://rightsstatements.org/vocab/NKC/1.0/",
    "Rights Notes": "No known copyright. Item is in public domain as it was published prior to 1923.",
    "Source": "<span>From: <a href=\"https://content.libraries.wsu.edu/digital/collection/propaganda/id/67\">Use More Potatoes</a></span>",
    "Subject": "World War, 1914-1918; War Posters, American",
    "Title": "Use More Potatoes",
    "Genre": "Political posters",
    "Type": "Image",
    "Repository": "WSU Libraries Digital Collections"
}