{
    "Creator": "J. E. Goossens.",
    "Date (Original)": "1942~",
    "Description": "61.5 x 100.5 cm. Color. Propaganda poster with an enlarged photograph of Marshal Petain and a red graphic of women and children grouped together against his heart.",
    "Digitization": "Original items were scanned as 600 dpi tiffs on a Zeutschel OS 14000 A0-LS scanner. They were converted to jpegs (sized at 3000 pixels on the long dimension) using Adobe Photoshop CS2 and subsequently uploaded into CONTENTdm.",
    "Identifier": "sc005f62-344",
    "Language": "French",
    "Publisher": "J. E. Goossens.",
    "Rights": "http://rightsstatements.org/vocab/NKC/1.0/",
    "Rights Notes": "No known copyright. Item is believed to be in public domain due to failure to comply with required formalities.",
    "Source": "<span>From: <a href=\"https://content.libraries.wsu.edu/digital/collection/propaganda/id/553\">Secours Nationa: ils ont Froid ils ont Faim Aidez-Moi a les Secourir</a></span>",
    "Subject": "World War, 1939-1945; War Posters, French",
    "Title": "Secours Nationa: ils ont Froid ils ont Faim Aidez-Moi a les Secourir",
    "Genre": "Political posters",
    "Type": "Image",
    "Repository": "WSU Libraries Digital Collections"
}