{
    "Creator": "American Red Cross.",
    "Date (Original)": "1916~",
    "Description": "70 x 106 cm. Black and white with red accents.  Recruitment poster for the Red Cross. Graphic background is a large red cross, in front of which a Red Cross nurse tends to a wounded soldier, and a mother and her children.",
    "Digitization": "Original items were scanned as 600 dpi tiffs on a Zeutschel OS 14000 A0-LS scanner. They were converted to jpegs (sized at 3000 pixels on the long dimension) using Adobe Photoshop CS2 they and subsequently uploaded into CONTENTdm.",
    "Identifier": "sc005f23-099",
    "Language": "English",
    "Publisher": "American Red Cross.",
    "Rights": "http://rightsstatements.org/vocab/NKC/1.0/",
    "Rights Notes": "No known copyright. Item is in public domain as it was published prior to 1923.",
    "Source": "<span>From: <a href=\"https://content.libraries.wsu.edu/digital/collection/propaganda/id/94\">What Can You Do?</a></span>",
    "Subject": "World War, 1914-1918; War Posters, American",
    "Title": "What Can You Do?",
    "Genre": "Political posters",
    "Type": "Image",
    "Repository": "WSU Libraries Digital Collections"
}